isoring/__init__.py
isoring/brute_forcer/__init__.py
isoring/brute_forcer/background_info.py
isoring/brute_forcer/brute_force_env.py
isoring/brute_forcer/cracker.py
isoring/brute_forcer/crackling.py
isoring/brute_forcer/hypothesis.py
isoring/brute_forcer/leak_functions.py
isoring/secrets/__init__.py
isoring/secrets/big_secret.py
isoring/secrets/bloominstein.py
isoring/secrets/iring.py
isoring/secrets/secret.py
isoring/security_sim/__init__.py
isoring/security_sim/data_load.py
isoring/security_sim/ui.py
isoring-0.1.6.dist-info/licenses/LICENSE
isoring-0.1.6.dist-info/METADATA
isoring-0.1.6.dist-info/WHEEL
isoring-0.1.6.dist-info/top_level.txt
isoring-0.1.6.dist-info/RECORD
