Metadata-Version: 2.4
Name: isoring
Version: 0.1.6
Summary: A structure for data security and a cracking environment.
Home-page: https://github.com/Changissnz/isoring
Author: Richard Pham
Author-email: Richard Pham <phamrichard45@gmail.com>
License-Expression: MIT
Project-URL: Homepage, https://github.com/changissnz/isoring
Project-URL: Issues, https://github.com/changissnz/isoring/issues
Classifier: Programming Language :: Python :: 3
Classifier: Operating System :: OS Independent
Requires-Python: >=3.9
License-File: LICENSE
Dynamic: author
Dynamic: home-page
Dynamic: license-file
